louieai/__init__.py
louieai/_client.py
louieai/_table_ai.py
louieai/_tracing.py
louieai/_upload.py
louieai/_version.py
louieai/auth.py
louieai/globals.py
louieai/py.typed
louieai/notebook/__init__.py
louieai/notebook/cursor.py
louieai/notebook/exceptions.py
louieai/notebook/streaming.py
louieai-0.7.1.dist-info/licenses/LICENSE
louieai-0.7.1.dist-info/licenses/NOTICE
louieai-0.7.1.dist-info/METADATA
louieai-0.7.1.dist-info/WHEEL
louieai-0.7.1.dist-info/top_level.txt
louieai-0.7.1.dist-info/RECORD
