Metadata-Version: 2.4
Name: louieai
Version: 0.7.1
Summary: Python client for Louie.ai (Graphistry's AI investigation platform)
Author-email: "Graphistry, Inc." <support@graphistry.com>
License-Expression: Apache-2.0
Project-URL: Documentation, https://louieai.readthedocs.io
Project-URL: Repository, https://github.com/graphistry/louie-py
Project-URL: Issue Tracker, https://github.com/graphistry/louie-py/issues
Project-URL: Changelog, https://github.com/graphistry/louie-py/blob/main/CHANGELOG.md
Keywords: Louie.ai,Graphistry,AI,client,investigation
Classifier: Development Status :: 3 - Alpha
Classifier: Intended Audience :: Developers
Classifier: Programming Language :: Python :: 3
Classifier: Programming Language :: Python :: 3.10
Classifier: Programming Language :: Python :: 3.11
Classifier: Programming Language :: Python :: 3.12
Classifier: Programming Language :: Python :: 3.13
Classifier: Topic :: Software Development :: Libraries :: Python Modules
Classifier: Topic :: Scientific/Engineering :: Information Analysis
Requires-Python: >=3.10
License-File: LICENSE
License-File: NOTICE
Requires-Dist: graphistry>=0.41.0
Requires-Dist: httpx>=0.28.0
Requires-Dist: pandas<4,>=2.0.0
Requires-Dist: pillow>=11.3.0
Requires-Dist: pyarrow>=14.0.0
Provides-Extra: dev
Requires-Dist: ruff>=0.12.0; extra == "dev"
Requires-Dist: mypy>=1.17.0; extra == "dev"
Requires-Dist: pyarrow-stubs; extra == "dev"
Requires-Dist: pytest>=8.4.0; extra == "dev"
Requires-Dist: pytest-cov>=5.0.0; extra == "dev"
Requires-Dist: pytest-xdist>=3.6.0; extra == "dev"
Requires-Dist: pre-commit>=4.2.0; extra == "dev"
Requires-Dist: detect-secrets>=1.5.0; extra == "dev"
Requires-Dist: mkdocs>=1.6.0; extra == "dev"
Requires-Dist: mkdocs-material>=9.6.0; extra == "dev"
Requires-Dist: mkdocs-jupyter>=0.24.0; extra == "dev"
Requires-Dist: nbclient>=0.10.2; extra == "dev"
Requires-Dist: python-dotenv>=1.0.0; extra == "dev"
Requires-Dist: ipython>=8.0.0; extra == "dev"
Requires-Dist: opentelemetry-api>=1.0.0; extra == "dev"
Provides-Extra: docs
Requires-Dist: mkdocs>=1.6.0; extra == "docs"
Requires-Dist: mkdocs-material>=9.6.0; extra == "docs"
Requires-Dist: mkdocstrings[python]>=0.24.0; extra == "docs"
Requires-Dist: mkdocs-jupyter>=0.24.0; extra == "docs"
Requires-Dist: nbclient>=0.10.2; extra == "docs"
Requires-Dist: ipykernel>=6.0.0; extra == "docs"
Dynamic: license-file
